pyjama/__init__.py
pyjama/strutils/__init__.py
pyjama/strutils/string_builder.py
pyjamaparty/__init__.py
pyjamaparty/patterns/__init__.py
pyjamaparty/patterns/singleton_pattern.py
pyjamaparty/strutils/__init__.py
pyjamaparty/strutils/string_builder.py
pyjamaparty/tests/patterns/__init__.py
pyjamaparty/tests/patterns/test_singleton_pattern.py
pyjamaparty/tests/strutils/__init__.py
pyjamaparty/tests/strutils/test_string_builder.py
pyjamaparty-0.2.dist-info/LICENSE
pyjamaparty-0.2.dist-info/METADATA
pyjamaparty-0.2.dist-info/WHEEL
pyjamaparty-0.2.dist-info/top_level.txt
pyjamaparty-0.2.dist-info/RECORD
