Metadata-Version: 2.1
Name: pyjamaparty
Version: 0.2
Summary: Set of casual python utilities
Home-page: http://github.com/krajasek/pyjamaparty
Author: Karthik Rajasekaran
Author-email: krajasek@gmail.com
License: MIT
Platform: UNKNOWN
Requires-Python: >=2.7
